eddmPrint/__init__.py
eddmPrint/colors.py
eddmPrint/printer.py
eddmPrint/templates.py
eddmprint-0.1.7.dist-info/licenses/LICENSE
eddmprint-0.1.7.dist-info/METADATA
eddmprint-0.1.7.dist-info/WHEEL
eddmprint-0.1.7.dist-info/top_level.txt
eddmprint-0.1.7.dist-info/RECORD
