Metadata-Version: 2.4
Name: eddmPrint
Version: 0.1.7
Summary: 색상과 위치 정보가 포함된 개선된 프린트 라이브러리 - 자동 초기화 및 다양한 출력 형식 지원
Home-page: https://github.com/eddmpython/eddmPrint
Author: eddmpython
Author-email: eddmpython@gmail.com
Keywords: print,logging,color,debug,console
Classifier: Development Status :: 4 - Beta
Classifier: Intended Audience :: Developers
Classifier: Programming Language :: Python :: 3
Classifier: Programming Language :: Python :: 3.6
Classifier: Programming Language :: Python :: 3.7
Classifier: Programming Language :: Python :: 3.8
Classifier: Programming Language :: Python :: 3.9
Classifier: License :: OSI Approved :: MIT License
Classifier: Operating System :: OS Independent
Classifier: Topic :: Software Development :: Libraries :: Python Modules
Classifier: Topic :: Utilities
Requires-Python: >=3.6
License-File: LICENSE
Dynamic: author
Dynamic: author-email
Dynamic: classifier
Dynamic: description
Dynamic: description-content-type
Dynamic: home-page
Dynamic: keywords
Dynamic: license-file
Dynamic: requires-python
Dynamic: summary
